click_mcp_server/__init__.py
click_mcp_server/__main__.py
click_mcp_server/cli.py
click_mcp_server/metadata.py
click_mcp_server/py.typed
click_mcp_server/server.py
click_mcp_server-0.1.0.dist-info/METADATA
click_mcp_server-0.1.0.dist-info/WHEEL
click_mcp_server-0.1.0.dist-info/entry_points.txt
click_mcp_server-0.1.0.dist-info/licenses/LICENSE.txt
click_mcp_server-0.1.0.dist-info/RECORD
