Metadata-Version: 2.4
Name: click-mcp-server
Version: 0.1.0
Summary: MCP server for any Click command line tool
Project-URL: Homepage, https://ofek.dev/click-mcp-server/
Project-URL: Sponsor, https://github.com/sponsors/ofek
Project-URL: Changelog, https://ofek.dev/click-mcp-server/changelog/
Project-URL: Tracker, https://github.com/ofek/click-mcp-server/issues
Project-URL: Source, https://github.com/ofek/click-mcp-server
Author-email: Ofek Lev <oss@ofek.dev>
License-Expression: MIT
License-File: LICENSE.txt
Keywords: ai,cli,click,mcp
Classifier: Development Status :: 4 - Beta
Classifier: Programming Language :: Python
Classifier: Programming Language :: Python :: 3.10
Classifier: Programming Language :: Python :: 3.11
Classifier: Programming Language :: Python :: 3.12
Classifier: Programming Language :: Python :: 3.13
Classifier: Programming Language :: Python :: 3.14
Classifier: Programming Language :: Python :: Implementation :: CPython
Classifier: Programming Language :: Python :: Implementation :: PyPy
Requires-Python: >=3.10
Requires-Dist: click
Requires-Dist: mcp
